{
  "info": {
    "_postman_id": "9eb89d48-eafe-4655-a532-fcf7245989d0",
    "name": "currency-conversion",
    "schema": "https://schema.getpostman.com/json/collection/v2.1.0/collection.json"
  },
  "item": [
    {
      "name": "exchange-rate-eur-usd",
      "request": {
        "method": "GET",
        "header": [],
        "url": {
          "raw": "localhost:3000/exchange-rate-eur-usd",
          "host": ["localhost"],
          "port": "3000",
          "path": ["exchange-rate-eur-usd"]
        }
      },
      "response": []
    },
    {
      "name": "conversion-usd-gbp",
      "request": {
        "method": "POST",
        "header": [],
        "body": {
          "mode": "raw",
          "raw": "{\n    \"valueUSD\": 5\n}",
          "options": {
            "raw": {
              "language": "json"
            }
          }
        },
        "url": {
          "raw": "localhost:3000/conversion-usd-gbp",
          "host": ["localhost"],
          "port": "3000",
          "path": ["conversion-usd-gbp"]
        }
      },
      "response": []
    },
    {
      "name": "conversion-eur-gbp",
      "request": {
        "method": "POST",
        "header": [],
        "body": {
          "mode": "raw",
          "raw": "{\n    \"valueEUR\": 8\n}",
          "options": {
            "raw": {
              "language": "json"
            }
          }
        },
        "url": {
          "raw": "localhost:3000/conversion-eur-gbp",
          "host": ["localhost"],
          "port": "3000",
          "path": ["conversion-eur-gbp"]
        }
      },
      "response": []
    },
    {
      "name": "conversion-sum-eur-gbp-to-cad",
      "request": {
        "method": "POST",
        "header": [],
        "body": {
          "mode": "raw",
          "raw": "{\n    \"valuesToAdd\": {\n        \"valEUR\": 15,\n        \"valGBP\": 12\n    }\n}",
          "options": {
            "raw": {
              "language": "json"
            }
          }
        },
        "url": {
          "raw": "localhost:3000/conversion-sum-eur-gbp-to-cad",
          "host": ["localhost"],
          "port": "3000",
          "path": ["conversion-sum-eur-gbp-to-cad"]
        }
      },
      "response": []
    }
  ]
}
